{
  "cities": [
    {
      "cityName": "Rosenau am Hengstpass",
      "country": "Austria",
      "emoji": "🇦🇹",
      "date": "2023-09-09T13:59:21.841Z",
      "notes": "",
      "position": {
        "lat": "47.68018294648414",
        "lng": "14.436035156250002"
      },
      "id": 1
    },
    {
      "cityName": "Unstrut-Hainich",
      "country": "Germany",
      "emoji": "🇩🇪",
      "date": "2023-09-09T13:59:24.034Z",
      "notes": "",
      "position": {
        "lat": "51.11041991029264",
        "lng": "10.502929687500002"
      },
      "id": 2
    },
    {
      "cityName": "Bertem",
      "country": "Belgium",
      "emoji": "🇧🇪",
      "date": "2023-09-09T13:59:27.754Z",
      "notes": "",
      "position": {
        "lat": "50.84757295365389",
        "lng": "4.570312500000001"
      },
      "id": 3
    }
  ]
}